Workbook

Sheet Criteria
A1: Criteria
A3: What matters to you
A4: Criterion | B4: Weight | D4: 1 is nice to have, 5 is decisive
A5: Commute | B5: 5
A6: Neighborhood | B6: 5
A7: Condition | B7: 4
A8: Kitchen | B8: 4
A9: Natural light | B9: 4
A10: Layout | B10: 3
A11: Yard or outdoor space | B11: 3
A12: Schools | B12: 3
A13: Storage | B13: 2
A14: Parking | B14: 2
A16: Total
A17: Total weight | B17: =SUM($B$5:$B$14)
A18: Highest possible score | B18: =$B$17*5 | D18: total weight x 5
B20: =IF($B$17=0,"Give at least one criterion a weight.","")

Sheet Homes
A1: Homes
A3: Score each home 1 to 5
A4: Home | B4: Asking price | C4: ='Criteria'!$A$5 | D4: ='Criteria'!$A$6 | E4: ='Criteria'!$A$7 | F4: ='Criteria'!$A$8 | G4: ='Criteria'!$A$9 | H4: ='Criteria'!$A$10 | I4: ='Criteria'!$A$11 | J4: ='Criteria'!$A$12 | K4: ='Criteria'!$A$13 | L4: ='Criteria'!$A$14 | M4: Score | N4: Of possible | O4: Check
A5: 123 Oak Street | B5: 425000 | C5: -2 | D5: 3 | E5: 3 | F5: 3 | G5: 3 | H5: 3 | I5: 3 | J5: 3 | K5: 3 | L5: 3 | M5: =IF($A5="","",$C5*'Criteria'!$B$5 + $D5*'Criteria'!$B$6 + $E5*'Criteria'!$B$7 + $F5*'Criteria'!$B$8 + $G5*'Criteria'!$B$9 + $H5*'Criteria'!$B$10 + $I5*'Criteria'!$B$11 + $J5*'Criteria'!$B$12 + $K5*'Criteria'!$B$13 + $L5*'Criteria'!$B$14) | N5: =IFERROR(IF($A5="","",$M5/'Criteria'!$B$18),"") | O5: =IF($A5="","",IF($B5="","Enter an asking price.",IF(OR($C5>5,$D5>5,$E5>5,$F5>5,$G5>5,$H5>5,$I5>5,$J5>5,$K5>5,$L5>5),"Scores go up to 5.",IF(OR($C5<0,$D5<0,$E5<0,$F5<0,$G5<0,$H5<0,$I5<0,$J5<0,$K5<0,$L5<0),"Scores cannot be negative.","READY"))))
A6: 88 Larch Avenue | B6: 399000 | C6: 3 | D6: 3 | E6: 3 | F6: 3 | G6: 3 | H6: 3 | I6: 3 | J6: 3 | K6: 3 | L6: 3 | M6: =IF($A6="","",$C6*'Criteria'!$B$5 + $D6*'Criteria'!$B$6 + $E6*'Criteria'!$B$7 + $F6*'Criteria'!$B$8 + $G6*'Criteria'!$B$9 + $H6*'Criteria'!$B$10 + $I6*'Criteria'!$B$11 + $J6*'Criteria'!$B$12 + $K6*'Criteria'!$B$13 + $L6*'Criteria'!$B$14) | N6: =IFERROR(IF($A6="","",$M6/'Criteria'!$B$18),"") | O6: =IF($A6="","",IF($B6="","Enter an asking price.",IF(OR($C6>5,$D6>5,$E6>5,$F6>5,$G6>5,$H6>5,$I6>5,$J6>5,$K6>5,$L6>5),"Scores go up to 5.",IF(OR($C6<0,$D6<0,$E6<0,$F6<0,$G6<0,$H6<0,$I6<0,$J6<0,$K6<0,$L6<0),"Scores cannot be negative.","READY"))))
A7: 17 Mill Lane | B7: 460000 | C7: 3 | D7: 3 | E7: 3 | F7: 3 | G7: 3 | H7: 3 | I7: 3 | J7: 3 | K7: 3 | L7: 3 | M7: =IF($A7="","",$C7*'Criteria'!$B$5 + $D7*'Criteria'!$B$6 + $E7*'Criteria'!$B$7 + $F7*'Criteria'!$B$8 + $G7*'Criteria'!$B$9 + $H7*'Criteria'!$B$10 + $I7*'Criteria'!$B$11 + $J7*'Criteria'!$B$12 + $K7*'Criteria'!$B$13 + $L7*'Criteria'!$B$14) | N7: =IFERROR(IF($A7="","",$M7/'Criteria'!$B$18),"") | O7: =IF($A7="","",IF($B7="","Enter an asking price.",IF(OR($C7>5,$D7>5,$E7>5,$F7>5,$G7>5,$H7>5,$I7>5,$J7>5,$K7>5,$L7>5),"Scores go up to 5.",IF(OR($C7<0,$D7<0,$E7<0,$F7<0,$G7<0,$H7<0,$I7<0,$J7<0,$K7<0,$L7<0),"Scores cannot be negative.","READY"))))
M8: =IF($A8="","",$C8*'Criteria'!$B$5 + $D8*'Criteria'!$B$6 + $E8*'Criteria'!$B$7 + $F8*'Criteria'!$B$8 + $G8*'Criteria'!$B$9 + $H8*'Criteria'!$B$10 + $I8*'Criteria'!$B$11 + $J8*'Criteria'!$B$12 + $K8*'Criteria'!$B$13 + $L8*'Criteria'!$B$14) | N8: =IFERROR(IF($A8="","",$M8/'Criteria'!$B$18),"") | O8: =IF($A8="","",IF($B8="","Enter an asking price.",IF(OR($C8>5,$D8>5,$E8>5,$F8>5,$G8>5,$H8>5,$I8>5,$J8>5,$K8>5,$L8>5),"Scores go up to 5.",IF(OR($C8<0,$D8<0,$E8<0,$F8<0,$G8<0,$H8<0,$I8<0,$J8<0,$K8<0,$L8<0),"Scores cannot be negative.","READY"))))
M9: =IF($A9="","",$C9*'Criteria'!$B$5 + $D9*'Criteria'!$B$6 + $E9*'Criteria'!$B$7 + $F9*'Criteria'!$B$8 + $G9*'Criteria'!$B$9 + $H9*'Criteria'!$B$10 + $I9*'Criteria'!$B$11 + $J9*'Criteria'!$B$12 + $K9*'Criteria'!$B$13 + $L9*'Criteria'!$B$14) | N9: =IFERROR(IF($A9="","",$M9/'Criteria'!$B$18),"") | O9: =IF($A9="","",IF($B9="","Enter an asking price.",IF(OR($C9>5,$D9>5,$E9>5,$F9>5,$G9>5,$H9>5,$I9>5,$J9>5,$K9>5,$L9>5),"Scores go up to 5.",IF(OR($C9<0,$D9<0,$E9<0,$F9<0,$G9<0,$H9<0,$I9<0,$J9<0,$K9<0,$L9<0),"Scores cannot be negative.","READY"))))
M10: =IF($A10="","",$C10*'Criteria'!$B$5 + $D10*'Criteria'!$B$6 + $E10*'Criteria'!$B$7 + $F10*'Criteria'!$B$8 + $G10*'Criteria'!$B$9 + $H10*'Criteria'!$B$10 + $I10*'Criteria'!$B$11 + $J10*'Criteria'!$B$12 + $K10*'Criteria'!$B$13 + $L10*'Criteria'!$B$14) | N10: =IFERROR(IF($A10="","",$M10/'Criteria'!$B$18),"") | O10: =IF($A10="","",IF($B10="","Enter an asking price.",IF(OR($C10>5,$D10>5,$E10>5,$F10>5,$G10>5,$H10>5,$I10>5,$J10>5,$K10>5,$L10>5),"Scores go up to 5.",IF(OR($C10<0,$D10<0,$E10<0,$F10<0,$G10<0,$H10<0,$I10<0,$J10<0,$K10<0,$L10<0),"Scores cannot be negative.","READY"))))
M11: =IF($A11="","",$C11*'Criteria'!$B$5 + $D11*'Criteria'!$B$6 + $E11*'Criteria'!$B$7 + $F11*'Criteria'!$B$8 + $G11*'Criteria'!$B$9 + $H11*'Criteria'!$B$10 + $I11*'Criteria'!$B$11 + $J11*'Criteria'!$B$12 + $K11*'Criteria'!$B$13 + $L11*'Criteria'!$B$14) | N11: =IFERROR(IF($A11="","",$M11/'Criteria'!$B$18),"") | O11: =IF($A11="","",IF($B11="","Enter an asking price.",IF(OR($C11>5,$D11>5,$E11>5,$F11>5,$G11>5,$H11>5,$I11>5,$J11>5,$K11>5,$L11>5),"Scores go up to 5.",IF(OR($C11<0,$D11<0,$E11<0,$F11<0,$G11<0,$H11<0,$I11<0,$J11<0,$K11<0,$L11<0),"Scores cannot be negative.","READY"))))
M12: =IF($A12="","",$C12*'Criteria'!$B$5 + $D12*'Criteria'!$B$6 + $E12*'Criteria'!$B$7 + $F12*'Criteria'!$B$8 + $G12*'Criteria'!$B$9 + $H12*'Criteria'!$B$10 + $I12*'Criteria'!$B$11 + $J12*'Criteria'!$B$12 + $K12*'Criteria'!$B$13 + $L12*'Criteria'!$B$14) | N12: =IFERROR(IF($A12="","",$M12/'Criteria'!$B$18),"") | O12: =IF($A12="","",IF($B12="","Enter an asking price.",IF(OR($C12>5,$D12>5,$E12>5,$F12>5,$G12>5,$H12>5,$I12>5,$J12>5,$K12>5,$L12>5),"Scores go up to 5.",IF(OR($C12<0,$D12<0,$E12<0,$F12<0,$G12<0,$H12<0,$I12<0,$J12<0,$K12<0,$L12<0),"Scores cannot be negative.","READY"))))

Sheet Costs
A1: Costs
A3: What each one costs you every month
A4: Home | B4: Loan payment | C4: Property tax | D4: Insurance | E4: HOA | F4: Commute | G4: Maintenance | H4: Total | J4: the figure your lender quoted
A5: ='Homes'!$A5 | B5: 2150 | C5: 390 | D5: 95 | E5: 0 | F5: 120 | G5: 180 | H5: =IF('Homes'!$A5="","",SUM($B5:$G5))
A6: ='Homes'!$A6 | B6: 1980 | C6: 340 | D6: 88 | E6: 145 | F6: 210 | G6: 165 | H6: =IF('Homes'!$A6="","",SUM($B6:$G6))
A7: ='Homes'!$A7 | B7: 2340 | C7: 455 | D7: 102 | E7: 0 | F7: 60 | G7: 195 | H7: =IF('Homes'!$A7="","",SUM($B7:$G7))
A8: ='Homes'!$A8 | H8: =IF('Homes'!$A8="","",SUM($B8:$G8))
A9: ='Homes'!$A9 | H9: =IF('Homes'!$A9="","",SUM($B9:$G9))
A10: ='Homes'!$A10 | H10: =IF('Homes'!$A10="","",SUM($B10:$G10))
A11: ='Homes'!$A11 | H11: =IF('Homes'!$A11="","",SUM($B11:$G11))
A12: ='Homes'!$A12 | H12: =IF('Homes'!$A12="","",SUM($B12:$G12))

Sheet Results
A1: Results
A3: Every home, side by side
A4: Home | B4: Score | C4: Of possible | D4: Cost per month | E4: Cost per point
A5: ='Homes'!$A5 | B5: ='Homes'!$M5 | C5: ='Homes'!$N5 | D5: ='Costs'!$H5 | E5: =IFERROR(IF(OR($B5="",$B5=0,$D5=""),"",$D5/$B5),"") | F5: =IFERROR(IF($E5="","",IF($E5=MIN($E$5:$E$12),"Most of what you want per dollar","")),"")
A6: ='Homes'!$A6 | B6: ='Homes'!$M6 | C6: ='Homes'!$N6 | D6: ='Costs'!$H6 | E6: =IFERROR(IF(OR($B6="",$B6=0,$D6=""),"",$D6/$B6),"") | F6: =IFERROR(IF($E6="","",IF($E6=MIN($E$5:$E$12),"Most of what you want per dollar","")),"")
A7: ='Homes'!$A7 | B7: ='Homes'!$M7 | C7: ='Homes'!$N7 | D7: ='Costs'!$H7 | E7: =IFERROR(IF(OR($B7="",$B7=0,$D7=""),"",$D7/$B7),"") | F7: =IFERROR(IF($E7="","",IF($E7=MIN($E$5:$E$12),"Most of what you want per dollar","")),"")
A8: ='Homes'!$A8 | B8: ='Homes'!$M8 | C8: ='Homes'!$N8 | D8: ='Costs'!$H8 | E8: =IFERROR(IF(OR($B8="",$B8=0,$D8=""),"",$D8/$B8),"") | F8: =IFERROR(IF($E8="","",IF($E8=MIN($E$5:$E$12),"Most of what you want per dollar","")),"")
A9: ='Homes'!$A9 | B9: ='Homes'!$M9 | C9: ='Homes'!$N9 | D9: ='Costs'!$H9 | E9: =IFERROR(IF(OR($B9="",$B9=0,$D9=""),"",$D9/$B9),"") | F9: =IFERROR(IF($E9="","",IF($E9=MIN($E$5:$E$12),"Most of what you want per dollar","")),"")
A10: ='Homes'!$A10 | B10: ='Homes'!$M10 | C10: ='Homes'!$N10 | D10: ='Costs'!$H10 | E10: =IFERROR(IF(OR($B10="",$B10=0,$D10=""),"",$D10/$B10),"") | F10: =IFERROR(IF($E10="","",IF($E10=MIN($E$5:$E$12),"Most of what you want per dollar","")),"")
A11: ='Homes'!$A11 | B11: ='Homes'!$M11 | C11: ='Homes'!$N11 | D11: ='Costs'!$H11 | E11: =IFERROR(IF(OR($B11="",$B11=0,$D11=""),"",$D11/$B11),"") | F11: =IFERROR(IF($E11="","",IF($E11=MIN($E$5:$E$12),"Most of what you want per dollar","")),"")
A12: ='Homes'!$A12 | B12: ='Homes'!$M12 | C12: ='Homes'!$N12 | D12: ='Costs'!$H12 | E12: =IFERROR(IF(OR($B12="",$B12=0,$D12=""),"",$D12/$B12),"") | F12: =IFERROR(IF($E12="","",IF($E12=MIN($E$5:$E$12),"Most of what you want per dollar","")),"")
A14: Summary
A15: Highest score | B15: =MAX($B$5:$B$12)
A16: Lowest monthly cost | B16: =MIN($D$5:$D$12)
A17: Best cost per point | B17: =MIN($E$5:$E$12)
B19: =IF(MAX($B$5:$B$12)=0,"Score at least one home to see results.","")

Sheet Reference
A1: Reference
A3: What this is not
A4: Not a valuation | C4: It does not estimate what a home is worth or what it should sell for.
A5: Not lending advice | C5: Enter the monthly payment your lender quoted. A spreadsheet guess would be worse than the real number.
A7: Terms
A8: Weight | C8: How much a criterion matters to you, 1 to 5.
A9: Score | C9: How well one home does on one criterion, 1 to 5.
A10: Of possible | C10: Your score as a share of the highest score any home could reach.
A11: Cost per point | C11: Monthly cost divided by score. Lower means more of what you want per dollar.
A13: Editable assumptions
A14: Assumption | B14: Default | C14: Change it on
A15: Criteria and weights | B15: 10 shown | C15: Criteria
A16: Score range | B16: 1 to 5 | C16: fixed
A17: Homes compared | B17: 8 available | C17: Homes
A19: Cell colors
C20: Enter your own numbers
C21: Calculated automatically
C22: Editable assumption
