Workbook

Sheet Practice
A1: Private Practice Planner
A3: Setup
A4: Weeks worked per year | B4: 46 | D4: allow for time off
A5: Currency | B5: $
A6: Target take-home | B6: 60000 | D6: per year, after your tax set-aside
A7: Tax set-aside | B7: 0.25 | D7: your own rate
A9: Caseload
A11: Fee tier | B11: Fee | C11: Sessions/week | D11: Attendance | E11: Attended/year | F11: Revenue/year | G11: Check
A12: Full fee | B12: 150 | C12: 10 | D12: 1 | E12: =IF(OR($C12="",$D12=""),"",$C12*$D12*$B$4) | F12: =IF(OR($B12="",$C12="",$D12=""),"",$B12*$C12*$D12*$B$4) | G12: =IF(AND($A12="",$B12="",$C12="",$D12=""),"",IF($A12="","Name this tier.",IF($B12="","Enter a fee.",IF($C12="","Enter sessions per week.",IF($D12="","Enter an attendance rate.",IF($D12>1,"Attendance cannot be above 100%.",IF($D12<0,"Attendance cannot be below 0%.",IF($B12<0,"Fee cannot be negative.",IF($C12<0,"Sessions per week cannot be negative.","READY")))))))))
E13: =IF(OR($C13="",$D13=""),"",$C13*$D13*$B$4) | F13: =IF(OR($B13="",$C13="",$D13=""),"",$B13*$C13*$D13*$B$4) | G13: =IF(AND($A13="",$B13="",$C13="",$D13=""),"",IF($A13="","Name this tier.",IF($B13="","Enter a fee.",IF($C13="","Enter sessions per week.",IF($D13="","Enter an attendance rate.",IF($D13>1,"Attendance cannot be above 100%.",IF($D13<0,"Attendance cannot be below 0%.",IF($B13<0,"Fee cannot be negative.",IF($C13<0,"Sessions per week cannot be negative.","READY")))))))))
E14: =IF(OR($C14="",$D14=""),"",$C14*$D14*$B$4) | F14: =IF(OR($B14="",$C14="",$D14=""),"",$B14*$C14*$D14*$B$4) | G14: =IF(AND($A14="",$B14="",$C14="",$D14=""),"",IF($A14="","Name this tier.",IF($B14="","Enter a fee.",IF($C14="","Enter sessions per week.",IF($D14="","Enter an attendance rate.",IF($D14>1,"Attendance cannot be above 100%.",IF($D14<0,"Attendance cannot be below 0%.",IF($B14<0,"Fee cannot be negative.",IF($C14<0,"Sessions per week cannot be negative.","READY")))))))))
E15: =IF(OR($C15="",$D15=""),"",$C15*$D15*$B$4) | F15: =IF(OR($B15="",$C15="",$D15=""),"",$B15*$C15*$D15*$B$4) | G15: =IF(AND($A15="",$B15="",$C15="",$D15=""),"",IF($A15="","Name this tier.",IF($B15="","Enter a fee.",IF($C15="","Enter sessions per week.",IF($D15="","Enter an attendance rate.",IF($D15>1,"Attendance cannot be above 100%.",IF($D15<0,"Attendance cannot be below 0%.",IF($B15<0,"Fee cannot be negative.",IF($C15<0,"Sessions per week cannot be negative.","READY")))))))))
E16: =IF(OR($C16="",$D16=""),"",$C16*$D16*$B$4) | F16: =IF(OR($B16="",$C16="",$D16=""),"",$B16*$C16*$D16*$B$4) | G16: =IF(AND($A16="",$B16="",$C16="",$D16=""),"",IF($A16="","Name this tier.",IF($B16="","Enter a fee.",IF($C16="","Enter sessions per week.",IF($D16="","Enter an attendance rate.",IF($D16>1,"Attendance cannot be above 100%.",IF($D16<0,"Attendance cannot be below 0%.",IF($B16<0,"Fee cannot be negative.",IF($C16<0,"Sessions per week cannot be negative.","READY")))))))))
E17: =IF(OR($C17="",$D17=""),"",$C17*$D17*$B$4) | F17: =IF(OR($B17="",$C17="",$D17=""),"",$B17*$C17*$D17*$B$4) | G17: =IF(AND($A17="",$B17="",$C17="",$D17=""),"",IF($A17="","Name this tier.",IF($B17="","Enter a fee.",IF($C17="","Enter sessions per week.",IF($D17="","Enter an attendance rate.",IF($D17>1,"Attendance cannot be above 100%.",IF($D17<0,"Attendance cannot be below 0%.",IF($B17<0,"Fee cannot be negative.",IF($C17<0,"Sessions per week cannot be negative.","READY")))))))))
A19: Totals
A20: Sessions per week | B20: =SUM($C$12:$C$17)
A21: Sessions attended per year | B21: =SUM($E$12:$E$17)
A22: Revenue per year | B22: =SUM($F$12:$F$17)
A23: Average fee per session held | B23: =IFERROR($B$22/$B$21,"") | D23: revenue ÷ sessions attended
A24: Average per slot on the calendar | B24: =IFERROR($B$22/($B$20*$B$4),"") | D24: counts the no-shows
B26: =IF($B$20=0,"Enter at least one fee tier with sessions per week.","")

Sheet Costs
A1: Costs
A3: Every month
A4: Item | B4: Per month
A5: Office rent | B5: 600
A6: Practice software | B6: 69
A7: Phone and internet | B7: 45
A8: Clinical supervision | B8: 150
A9: Bookkeeping | B9: 60
A10: Directory listings | B10: 30
A11: Other | B11: 0
A16: Monthly total | B16: =SUM($B$5:$B$14)
A18: Once a year
A19: Item | B19: Per year
A20: Liability insurance | B20: 600
A21: License renewal | B21: 200
A22: Continuing education | B22: 500
A23: Professional membership | B23: 300
A24: Other | B24: 0
A29: Annual total | B29: =SUM($B$20:$B$27)
A31: Total
A32: Costs per year | B32: =$B$16*12+$B$29

Sheet Results
A1: Results
A3: As things stand
A4: Revenue | B4: ='Practice'!$B$22
A5: Costs | B5: ='Costs'!$B$32
A6: Before tax | B6: =IF(OR($B$4="",$B$5=""),"",$B$4-$B$5)
A7: Tax set-aside | B7: =IF($B$6="","",MAX(0,$B$6)*'Practice'!$B$7)
A8: Take-home | B8: =IF($B$6="","",$B$6-$B$7)
A9: Target | B9: ='Practice'!$B$6
A10: Difference | B10: =IF($B$8="","",$B$8-$B$9) | D10: negative means short of target
A12: What the target needs
A13: Revenue needed | B13: =IFERROR('Practice'!$B$6/(1-'Practice'!$B$7)+'Costs'!$B$32,"")
A14: Sessions to cover costs | B14: =IFERROR(ROUNDUP('Costs'!$B$32/'Practice'!$B$23,0),"") | D14: held sessions per year
A15: Sessions to reach target | B15: =IFERROR(ROUNDUP($B$13/'Practice'!$B$23,0),"") | D15: held sessions per year
A16: Slots per week to reach target | B16: =IFERROR(ROUNDUP($B$13/('Practice'!$B$24*'Practice'!$B$4),0),"") | D16: counts the no-shows
B17: =IF('Practice'!$B$7>=1,"A tax set-aside of 100% or more leaves nothing to take home.","")
A19: How many reduced-fee slots you can carry
A20: Full fee | B20: 150
A21: Reduced fee | B21: 80
A22: Slots per week | B22: 22
A23: Attendance | B23: 0.9
A24: Reduced-fee slots | B24: =IFERROR(IF(OR($B$20="",$B$21="",$B$22="",$B$23="",$B$13=""),"",IF($B$20<=$B$21,"",ROUNDDOWN(MIN($B$22,MAX(0,($B$22*$B$20-$B$13/('Practice'!$B$4*$B$23))/($B$20-$B$21))),0))),"") | D24: and still reach the target
B25: =IF(OR($B$20="",$B$21="",$B$22="",$B$23=""),"",IF($B$20<=$B$21,"The reduced fee has to be below the full fee.",IF($B$24="","",IF($B$24<=0,"At this target every slot needs to be at the full fee.",IF($B$24>=$B$22,"The target is covered even with every slot at the reduced fee.","")))))

Sheet Reference
A1: Reference
A3: What this is not
A4: Not advice | C4: Arithmetic on the numbers you enter. It does not recommend a fee, a tax rate, a caseload or a sliding-scale policy.
A5: No clinical content | C5: Nothing here concerns a client, a diagnosis or a treatment.
A6: Not a tax return | C6: The tax set-aside is a rate you choose. Check it with your accountant.
A8: Terms
A9: Session held | C9: A session that actually happened. No-shows are not held sessions.
A10: Slot | C10: A place on your calendar. Some slots do not become held sessions.
A11: Attendance | C11: Held sessions ÷ slots. 90% means one slot in ten does not happen.
A12: Average per slot | C12: What a calendar slot is worth on average once no-shows are counted.
A13: Take-home | C13: Revenue minus costs minus your tax set-aside.
A14: Reduced-fee slots | C14: How many slots can be at the reduced fee with the target still reached.
A16: Editable assumptions
A17: Assumption | B17: Default | C17: Change it on
A18: Weeks worked per year | B18: 46 | C18: Practice
A19: Tax set-aside | B19: 25% | C19: Practice · your own rate
A20: Attendance per tier | B20: 85-90% | C20: Practice · use your own history
A21: Fee tiers | B21: 4 shown, 6 available | C21: Practice
A23: Cell colors
C24: Enter your own numbers
C25: Calculated automatically
C26: Editable assumption
